VeriSnip/__init__.py
VeriSnip/vs_build.py
VeriSnip/vs_build_old.py
VeriSnip/vs_colours.py
verisnip-0.0.3.dist-info/licenses/LICENSE
verisnip-0.0.3.dist-info/METADATA
verisnip-0.0.3.dist-info/WHEEL
verisnip-0.0.3.dist-info/entry_points.txt
verisnip-0.0.3.dist-info/top_level.txt
verisnip-0.0.3.dist-info/RECORD
