Metadata-Version: 2.4
Name: VeriSnip
Version: 0.0.3
Summary: A small example package
Author-email: Pedro Nuno de Melo Antunes <pedronmantunes@gmail.com>
License-Expression: Apache-2.0
Project-URL: Homepage, https://github.com/LogicoreDesign/VT-Tool.git
Project-URL: Issues, https://github.com/LogicoreDesign/VT-Tool/issues
Classifier: Programming Language :: Python :: 3
Classifier: Operating System :: OS Independent
Requires-Python: >=3.9
License-File: LICENSE
Dynamic: license-file
